odoo/addons/project_timeline_hr_timesheet/README.rst
odoo/addons/project_timeline_hr_timesheet/__init__.py
odoo/addons/project_timeline_hr_timesheet/__manifest__.py
odoo/addons/project_timeline_hr_timesheet/i18n/de.po
odoo/addons/project_timeline_hr_timesheet/i18n/es.po
odoo/addons/project_timeline_hr_timesheet/i18n/he.po
odoo/addons/project_timeline_hr_timesheet/i18n/it.po
odoo/addons/project_timeline_hr_timesheet/i18n/project_timeline_hr_timesheet.pot
odoo/addons/project_timeline_hr_timesheet/readme/CONTRIBUTORS.rst
odoo/addons/project_timeline_hr_timesheet/readme/DESCRIPTION.rst
odoo/addons/project_timeline_hr_timesheet/static/description/icon.png
odoo/addons/project_timeline_hr_timesheet/static/description/index.html
odoo/addons/project_timeline_hr_timesheet/static/src/scss/project_timeline_hr_timesheet.scss
odoo/addons/project_timeline_hr_timesheet/templates/assets.xml
odoo/addons/project_timeline_hr_timesheet/views/project_task_view.xml
odoo13_addon_project_timeline_hr_timesheet-13.0.1.0.1.dev6.dist-info/METADATA
odoo13_addon_project_timeline_hr_timesheet-13.0.1.0.1.dev6.dist-info/WHEEL
odoo13_addon_project_timeline_hr_timesheet-13.0.1.0.1.dev6.dist-info/top_level.txt
odoo13_addon_project_timeline_hr_timesheet-13.0.1.0.1.dev6.dist-info/RECORD
